canopy/__init__.py
canopy/_version.py
canopy/core/__init__.py
canopy/core/constants.py
canopy/core/field.py
canopy/core/frameops.py
canopy/core/raster.py
canopy/core/redspec.py
canopy/grid/__init__.py
canopy/grid/grid_abc.py
canopy/grid/grid_empty.py
canopy/grid/grid_lonlat.py
canopy/grid/grid_sites.py
canopy/grid/registry.py
canopy/json/__init__.py
canopy/json/json_functions.py
canopy/json/json_registry.py
canopy/json/run_json.py
canopy/readers/__init__.py
canopy/readers/fluxnet2015.py
canopy/readers/lpjguess.py
canopy/readers/registry.py
canopy/source_data/__init__.py
canopy/source_data/registry.py
canopy/source_data/data/fluxnet2015.json
canopy/source_data/data/lpjguess.json
canopy/sources/__init__.py
canopy/sources/registry.py
canopy/sources/source_abc.py
canopy/sources/source_fluxnet2015.py
canopy/sources/source_lpjguess.py
canopy/tests/__init__.py
canopy/tests/test_distribution.py
canopy/tests/test_latitudinal_plot.py
canopy/tests/test_map.py
canopy/tests/test_multiple_figs.py
canopy/tests/test_red_space_lonlat.py
canopy/tests/test_red_space_sites.py
canopy/tests/test_static.py
canopy/tests/test_ts.py
canopy/tests/test_data/aaet_global_sites.out.gz
canopy/tests/test_data/anpp_spain_1990_2010.out.gz
canopy/tests/test_data/anpp_spain_1990_2010_mod.out.gz
canopy/tests/test_data/registry.json
canopy/tests/test_data/registry.py
canopy/util/__init__.py
canopy/util/checks.py
canopy/util/compare_ts.py
canopy/util/fieldops.py
canopy/util/overlap.py
canopy/util/sites.py
canopy/visualization/__init__.py
canopy/visualization/distribution_plot.py
canopy/visualization/latitudinal_plot.py
canopy/visualization/map.py
canopy/visualization/multiple_figs.py
canopy/visualization/plot_functions.py
canopy/visualization/projections.py
canopy/visualization/static_plot.py
canopy/visualization/taylor_diagram.py
canopy/visualization/time_series.py
canopy_tools-0.9.1.dist-info/licenses/LICENSE
canopy_tools-0.9.1.dist-info/METADATA
canopy_tools-0.9.1.dist-info/WHEEL
canopy_tools-0.9.1.dist-info/top_level.txt
canopy_tools-0.9.1.dist-info/RECORD
