Metadata-Version: 2.4
Name: canopy-tools
Version: 0.9.1
Summary: A python package to analyse LSM and DGVM outputs
Author-email: "David M. Belda" <david.belda@kit.edu>, Adrien Damseaux <adrien.damseaux@kit.edu>
License: MPL-2.0
Project-URL: Homepage, https://codebase.helmholtz.cloud/canopy/canopy
Keywords: climate outputs,dgvm,land surface model,visualization
Classifier: Development Status :: 1 - Planning
Classifier: Intended Audience :: Science/Research
Classifier: Intended Audience :: Developers
Classifier: Operating System :: OS Independent
Classifier: Topic :: Scientific/Engineering
Classifier: Programming Language :: Python :: 3.12
Classifier: Programming Language :: Python :: 3.13
Classifier: Typing :: Typed
Requires-Python: >=3.12
License-File: LICENSE
Requires-Dist: pandas>=2.2.0
Requires-Dist: xarray>=2025.3.0
Requires-Dist: numpy>=2.2.0
Requires-Dist: matplotlib>=3.10.0
Requires-Dist: typing_extensions>=4.13.0
Requires-Dist: tqdm>=4.67.0
Requires-Dist: cartopy>=0.24.0
Requires-Dist: seaborn>=0.13.0
Requires-Dist: scipy>=1.15.0
Requires-Dist: jenkspy>=0.4.0
Requires-Dist: regionmask>=0.13.0
Requires-Dist: pyjanitor>=0.31.0
Requires-Dist: numba>=0.61.2
Requires-Dist: geocat-viz>=2025.07.0
Provides-Extra: sphinx
Requires-Dist: sphinx; extra == "sphinx"
Requires-Dist: sphinx-rtd-theme; extra == "sphinx"
Provides-Extra: dev
Requires-Dist: pandas-stubs>=2.2.0; extra == "dev"
Requires-Dist: types-seaborn>=0.13.0; extra == "dev"
Requires-Dist: scipy-stubs>=1.15.0; extra == "dev"
Requires-Dist: types-tqdm>=4.67.0; extra == "dev"
Requires-Dist: xarray-stubs>=2025.3.0; extra == "dev"
Requires-Dist: mypy>=1.0.0; extra == "dev"
Dynamic: license-file
